helveg_mono_test/__init__.py
helveg_mono_test/hello.py
helveg_mono_test_dep/__init__.py
helveg_mono_test_dep/hello.py
helveg_mono_test-1.0.11.dist-info/METADATA
helveg_mono_test-1.0.11.dist-info/WHEEL
helveg_mono_test-1.0.11.dist-info/RECORD
