Metadata-Version: 2.4
Name: helveg-mono-test
Version: 1.0.11
Summary: Automatically generated by Nx.
Requires-Python: >=3.9
